sgtlib/__init__.py
sgtlib/entrypoints.py
sgtlib/modules.py
sgtlib/apps/__init__.py
sgtlib/apps/cli_app.py
sgtlib/apps/gui_app.py
sgtlib/apps/lib_app.py
sgtlib/apps/controllers/__init__.py
sgtlib/apps/controllers/ai_controller.py
sgtlib/apps/controllers/base_controller.py
sgtlib/apps/controllers/graph_controller.py
sgtlib/apps/controllers/image_controller.py
sgtlib/apps/controllers/main_controller.py
sgtlib/apps/controllers/project_controller.py
sgtlib/apps/controllers/theme_manager.py
sgtlib/apps/models/__init__.py
sgtlib/apps/models/checkbox_model.py
sgtlib/apps/models/image_provider.py
sgtlib/apps/models/imagegrid_model.py
sgtlib/apps/models/table_model.py
sgtlib/apps/models/tree_model.py
sgtlib/apps/qml/MainWindow.qml
sgtlib/apps/qml/assets/icons/3d_icon.png
sgtlib/apps/qml/assets/icons/approve_icon.png
sgtlib/apps/qml/assets/icons/back_icon.png
sgtlib/apps/qml/assets/icons/brightness_icon.png
sgtlib/apps/qml/assets/icons/cancel_icon.png
sgtlib/apps/qml/assets/icons/crop_icon.png
sgtlib/apps/qml/assets/icons/crop_image_icon.png
sgtlib/apps/qml/assets/icons/delete_icon.png
sgtlib/apps/qml/assets/icons/edit_icon.png
sgtlib/apps/qml/assets/icons/expand_down_icon.png
sgtlib/apps/qml/assets/icons/expand_right_icon.png
sgtlib/apps/qml/assets/icons/graph_icon.png
sgtlib/apps/qml/assets/icons/hide_panel.png
sgtlib/apps/qml/assets/icons/left_right_arrow.png
sgtlib/apps/qml/assets/icons/next_icon.png
sgtlib/apps/qml/assets/icons/notify_active_icon.png
sgtlib/apps/qml/assets/icons/notify_icon.png
sgtlib/apps/qml/assets/icons/play_icon.png
sgtlib/apps/qml/assets/icons/rate_icon.png
sgtlib/apps/qml/assets/icons/reload_icon.png
sgtlib/apps/qml/assets/icons/replay_icon.png
sgtlib/apps/qml/assets/icons/rescale_icon.png
sgtlib/apps/qml/assets/icons/save_icon.png
sgtlib/apps/qml/assets/icons/show_panel.png
sgtlib/apps/qml/assets/icons/square_icon.png
sgtlib/apps/qml/assets/icons/star-full.png
sgtlib/apps/qml/assets/icons/star-half.png
sgtlib/apps/qml/assets/icons/star-none.png
sgtlib-3.7.5.dist-info/licenses/AUTHORS.rst
sgtlib-3.7.5.dist-info/licenses/LICENSE
sgtlib-3.7.5.dist-info/licenses/license.txt
sgtlib-3.7.5.dist-info/METADATA
sgtlib-3.7.5.dist-info/WHEEL
sgtlib-3.7.5.dist-info/entry_points.txt
sgtlib-3.7.5.dist-info/top_level.txt
sgtlib-3.7.5.dist-info/RECORD
