Metadata-Version: 2.4
Name: sgtlib
Version: 3.7.5
Summary: A software tool for graph theory analysis of microscopy images.
Author-email: Dickson Owuor <owuordickson@gmail.com>, "Drew A. Vecchio" <vecdrew@umich.edu>, Kody Whisnant <kgwhis@umich.edu>, Alain Kadar <alaink@umich.edu>, Xiong Ye Xiao <xiongyex@usc.edu>, Nicholas Kotov <kotov@umich.edu>
Maintainer-email: Dickson Owuor <owuordickson@gmail.com>
License:                     GNU GENERAL PUBLIC LICENSE
Project-URL: Homepage, https://github.com/owuordickson/structural-gt
Project-URL: Kotov, https://kotov.engin.umich.edu/
Project-URL: COMPASS, https://compass.engin.umich.edu/
Project-URL: Documentation, https://structural-gt.readthedocs.io
Project-URL: Repository, https://github.com/owuordickson/structural-gt.git
Project-URL: Bug Tracker, https://github.com/owuordickson/structural-gt/issues
Project-URL: Changelog, https://github.com/owuordickson/structural-gt/blob/main/CHANGELOG.md
Keywords: nano-particles,nano-structures,graph-theory
Classifier: Development Status :: 4 - Beta
Classifier: Programming Language :: Python :: 3.12
Classifier: Programming Language :: Python :: 3.13
Classifier: License :: OSI Approved :: GNU General Public License v3 (GPLv3)
Classifier: Operating System :: OS Independent
Classifier: Intended Audience :: Science/Research
Classifier: Topic :: Scientific/Engineering :: Artificial Intelligence
Requires-Python: >=3.12
License-File: LICENSE
License-File: license.txt
License-File: AUTHORS.rst
Requires-Dist: numpy==2.2.6
Requires-Dist: pandas==2.3.2
Requires-Dist: scipy==1.16.2
Requires-Dist: gsd==4.0.0
Requires-Dist: igraph==0.11.9
Requires-Dist: matplotlib==3.10.6
Requires-Dist: networkx==3.5
Requires-Dist: scikit-image==0.25.2
Requires-Dist: opencv-python>=4.12.0
Requires-Dist: pillow==11.3.0
Requires-Dist: PySide6==6.9.2
Requires-Dist: kneed==0.8.5
Requires-Dist: xlsxwriter==3.2.9
Requires-Dist: requests==2.32.5
Requires-Dist: dropbox==12.0.2
Requires-Dist: cryptography==46.0.1
Requires-Dist: scikit-learn==1.7.2
Provides-Extra: ovito
Requires-Dist: ovito>=3.13.0; extra == "ovito"
Dynamic: license-file
